hypothit/__init__.py
hypothit/__main__.py
hypothit/cli.py
hypothit-0.1.0.dist-info/AUTHORS.rst
hypothit-0.1.0.dist-info/LICENSE
hypothit-0.1.0.dist-info/METADATA
hypothit-0.1.0.dist-info/WHEEL
hypothit-0.1.0.dist-info/entry_points.txt
hypothit-0.1.0.dist-info/top_level.txt
hypothit-0.1.0.dist-info/RECORD
